pyfileapi/__init__.py
pyfileapi/_main.py
pyfileapi/search.py
pyfileapi/search_helpers.py
pyfileapi-0.0.3.dist-info/LICENSE
pyfileapi-0.0.3.dist-info/METADATA
pyfileapi-0.0.3.dist-info/WHEEL
pyfileapi-0.0.3.dist-info/entry_points.txt
pyfileapi-0.0.3.dist-info/top_level.txt
pyfileapi-0.0.3.dist-info/RECORD
