Metadata-Version: 2.1
Name: pyfileapi
Version: 0.0.3
Summary: A wrapper around the stdlib file functions
Home-page: https://github.com/thenextbigthingthisdecade/pyfile
Author: Prakhar Nagpal
Author-email: thenextbigthingthisdecade@gmail.com
License: MIT
Classifier: License :: OSI Approved :: MIT License
Classifier: Programming Language :: Python :: 3
Classifier: Programming Language :: Python :: 3 :: Only
Classifier: Programming Language :: Python :: Implementation :: CPython
Classifier: Programming Language :: Python :: Implementation :: PyPy
Requires-Python: >=3.7
License-File: LICENSE
Provides-Extra: test
Requires-Dist: pytest ; extra == 'test'
